{
  "openapi": "3.0.1",
  "info": {
    "title": "Healthcare.Api",
    "version": "1.0"
  },
  "paths": {
    "/appointments": {
      "post": {
        "tags": [
          "Appointments"
        ],
        "requestBody": {
          "content": {
            "application/json": {
              "schema": {
                "$ref": "#/components/schemas/CreateAppointmentRequest"
              }
            },
            "text/json": {
              "schema": {
                "$ref": "#/components/schemas/CreateAppointmentRequest"
              }
            },
            "application/*+json": {
              "schema": {
                "$ref": "#/components/schemas/CreateAppointmentRequest"
              }
            }
          }
        },
        "responses": {
          "200": {
            "description": "Success"
          }
        }
      }
    },
    "/appointments/appointments/{id}": {
      "delete": {
        "tags": [
          "Appointments"
        ],
        "parameters": [
          {
            "name": "id",
            "in": "path",
            "required": true,
            "schema": {
              "type": "string",
              "format": "uuid"
            }
          }
        ],
        "responses": {
          "200": {
            "description": "Success"
          }
        }
      }
    },
    "/doctors/{id}/availability": {
      "get": {
        "tags": [
          "Doctors"
        ],
        "parameters": [
          {
            "name": "id",
            "in": "path",
            "required": true,
            "schema": {
              "type": "string",
              "format": "uuid"
            }
          },
          {
            "name": "from",
            "in": "query",
            "schema": {
              "type": "string",
              "format": "date-time"
            }
          },
          {
            "name": "to",
            "in": "query",
            "schema": {
              "type": "string",
              "format": "date-time"
            }
          },
          {
            "name": "slot",
            "in": "query",
            "schema": {
              "type": "integer",
              "format": "int32"
            }
          }
        ],
        "responses": {
          "200": {
            "description": "Success"
          }
        }
      }
    }
  },
  "components": {
    "schemas": {
      "CreateAppointmentRequest": {
        "type": "object",
        "properties": {
          "doctorId": {
            "type": "string",
            "format": "uuid"
          },
          "patientId": {
            "type": "string",
            "format": "uuid"
          },
          "startUtc": {
            "type": "string",
            "format": "date-time"
          },
          "durationMinutes": {
            "type": "integer",
            "format": "int32"
          }
        },
        "additionalProperties": false
      }
    }
  }
}